flaxkv2/__init__.py
flaxkv2/__main__.py
flaxkv2/auto_close.py
flaxkv2/cli.py
flaxkv2/config.py
flaxkv2/display.py
flaxkv2/instance_manager.py
flaxkv2/client/__init__.py
flaxkv2/client/async_zmq_client.py
flaxkv2/client/connection_pool.py
flaxkv2/client/nested_remote.py
flaxkv2/client/zmq_client.py
flaxkv2/core/__init__.py
flaxkv2/core/base_leveldb_dict.py
flaxkv2/core/cached_leveldb_dict.py
flaxkv2/core/nested_structures.py
flaxkv2/core/raw_leveldb_dict.py
flaxkv2/inspector/__init__.py
flaxkv2/inspector/cli.py
flaxkv2/serialization/__init__.py
flaxkv2/serialization/decoder.py
flaxkv2/serialization/encoder.py
flaxkv2/serialization/value_meta.py
flaxkv2/server/__init__.py
flaxkv2/server/daemon.py
flaxkv2/server/daemon_runner.py
flaxkv2/server/zmq_server.py
flaxkv2/utils/__init__.py
flaxkv2/utils/bloom.py
flaxkv2/utils/config_loader.py
flaxkv2/utils/key_manager.py
flaxkv2/utils/keygen.py
flaxkv2/utils/log.py
flaxkv2/utils/rwlock.py
flaxkv2/utils/ttl_cleanup.py
flaxkv2/utils/unified_cache.py
flaxkv2/vector/__init__.py
flaxkv2/vector/store.py
flaxkv2-0.1.5.dist-info/METADATA
flaxkv2-0.1.5.dist-info/WHEEL
flaxkv2-0.1.5.dist-info/entry_points.txt
flaxkv2-0.1.5.dist-info/licenses/LICENSE
flaxkv2-0.1.5.dist-info/RECORD
