Metadata-Version: 2.4
Name: flaxkv2
Version: 0.1.5
Summary: A high-performance dictionary database.
Project-URL: Homepage, https://github.com/KenyonY/flaxkv2
Project-URL: Documentation, https://github.com/KenyonY/flaxkv2#flaxkv2
Project-URL: Issues, https://github.com/KenyonY/flaxkv2/issues
Project-URL: Source, https://github.com/KenyonY/flaxkv2
Author-email: "K.Y" <beidongjiedeguang@gmail.com>
License-File: LICENSE
Keywords: Deep Learning,Machine Learning,leveldb,on-disk dict,persistent-storage
Classifier: Development Status :: 5 - Production/Stable
Classifier: Operating System :: OS Independent
Classifier: Programming Language :: Python :: 3
Requires-Python: >=3.10
Requires-Dist: cryptography
Requires-Dist: fire
Requires-Dist: lz4
Requires-Dist: mmh3
Requires-Dist: msgpack
Requires-Dist: msgspec>=0.18.4
Requires-Dist: numpy
Requires-Dist: orjson>=3.9
Requires-Dist: plyvel-ci>=1.5.0; sys_platform == 'darwin'
Requires-Dist: plyvel-ci>=1.5.0; sys_platform == 'linux' and platform_machine == 'aarch64'
Requires-Dist: plyvel-ci>=1.5.0; sys_platform == 'win32'
Requires-Dist: plyvel>=1.5.0; sys_platform == 'linux' and platform_machine == 'x86_64'
Requires-Dist: psutil
Requires-Dist: pytz
Requires-Dist: pyzmq>=25.0.0
Requires-Dist: rich
Requires-Dist: tomli>=2.0.0; python_version < '3.11'
Requires-Dist: typing-extensions>=4.7.1; python_version < '3.11'
Provides-Extra: full
Requires-Dist: hnswlib>=0.7.0; extra == 'full'
Requires-Dist: mcp>=1.0.0; extra == 'full'
Requires-Dist: pandas; extra == 'full'
Provides-Extra: mcp
Requires-Dist: mcp>=1.0.0; extra == 'mcp'
Provides-Extra: pandas
Requires-Dist: pandas; extra == 'pandas'
Provides-Extra: test
Requires-Dist: pandas; extra == 'test'
Requires-Dist: pytest; extra == 'test'
Requires-Dist: pytest-cov; extra == 'test'
Requires-Dist: pytest-xdist; extra == 'test'
Provides-Extra: vector
Requires-Dist: hnswlib>=0.7.0; extra == 'vector'
